{"accepted":true,"author":"Maiden","kingdom":"Plantae","family":"Fabaceae","name":"Acacia jennerae","rank":"Species","url":"/taxon/urn:lsid:ipni.org:names:470623-1","fqId":"urn:lsid:ipni.org:names:470623-1","images":[{"thumbnail":"//d2seqvvyy3b8p2.cloudfront.net/5d0b78b02ee889c69419b1ac007a76d4.jpg","fullsize":"//d2seqvvyy3b8p2.cloudfront.net/9649ea4e983bc35df471ec33f7c55043.jpg","caption":"Acacia jennerae"},{"thumbnail":"//d2seqvvyy3b8p2.cloudfront.net/f3189b39f9593c6eb8ec4d7885cbfda0.jpg","fullsize":"//d2seqvvyy3b8p2.cloudfront.net/e600e451120c03dffc5b099c279551a6.jpg","caption":"Acacia jennerae"},{"thumbnail":"//d2seqvvyy3b8p2.cloudfront.net/ac4d0b143bd18d29968071b2610a289f.jpg","fullsize":"//d2seqvvyy3b8p2.cloudfront.net/aa54fc03b28cc52ed159761707bb4487.jpg","caption":"A specimen from Kew's Herbarium"}]}