{"accepted":true,"author":"L.","kingdom":"Plantae","family":"Poaceae","name":"Agrostis canina","rank":"Species","snippet":" <b>Common Name</b>: brown bent grass","url":"/taxon/urn:lsid:ipni.org:names:385537-1","fqId":"urn:lsid:ipni.org:names:385537-1","images":[{"thumbnail":"//d2seqvvyy3b8p2.cloudfront.net/8908f5cce6be2a1dc4969540bfe225b9.jpg","fullsize":"//d2seqvvyy3b8p2.cloudfront.net/8afab2694cfabef8f77cd5550fce70ac.jpg","caption":"Germany, Sturms Flora von Deutschland (1900-1906)"},{"thumbnail":"//d2seqvvyy3b8p2.cloudfront.net/461ac5f496a94680f161398544b33340.jpg","fullsize":"//d2seqvvyy3b8p2.cloudfront.net/66f79c593555c22020ca04508de30018.jpg","caption":"A specimen from Kew's Herbarium"},{"thumbnail":"//d2seqvvyy3b8p2.cloudfront.net/65fef934a880cbe639fb03b3d70b4a52.jpg","fullsize":"//d2seqvvyy3b8p2.cloudfront.net/ac4bd96423491c884d8e00690db00a94.jpg","caption":"A specimen from Kew's Herbarium"}]}