{"accepted":true,"author":"Paláu","kingdom":"Plantae","family":"Verbenaceae","name":"Aloysia citrodora","rank":"Species","snippet":" <b>General</b>: Synonym: <em>Aloysia</em> <em>triphylla</em> (L’Hér.) Britton (1925: 140).","url":"/taxon/urn:lsid:ipni.org:names:1015994-1","fqId":"urn:lsid:ipni.org:names:1015994-1","images":[{"thumbnail":"//d2seqvvyy3b8p2.cloudfront.net/773544a20cdc82939a3776b396d39374.jpg","fullsize":"//d2seqvvyy3b8p2.cloudfront.net/abd8acccd1690e82394f5239f9795c6a.jpg","caption":"A specimen from Kew's Herbarium"},{"thumbnail":"//d2seqvvyy3b8p2.cloudfront.net/1eb6b81bcff8a8e271ba667b3c0f3597.jpg","fullsize":"//d2seqvvyy3b8p2.cloudfront.net/4358b28e4c893d9dc01deea975a618cb.jpg","caption":"Aloysia citrodora"},{"thumbnail":"//d2seqvvyy3b8p2.cloudfront.net/cafe906b075f706dbab1532b66616421.jpg","fullsize":"//d2seqvvyy3b8p2.cloudfront.net/051c1b8ef314f8088394a9b0048220e4.jpg","caption":"Aloysia citrodora"}]}