{"accepted":true,"author":"L.","kingdom":"Plantae","family":"Plantaginaceae","name":"Antirrhinum majus","rank":"Species","snippet":" <b>Common Name</b>: snapdragon","url":"/taxon/urn:lsid:ipni.org:names:799180-1","fqId":"urn:lsid:ipni.org:names:799180-1","images":[{"thumbnail":"//d2seqvvyy3b8p2.cloudfront.net/67801502bbdaf63581b31189689889d6.jpg","fullsize":"//d2seqvvyy3b8p2.cloudfront.net/aa2f7261d6a46898cf592a365803a396.jpg","caption":"Antirrhinum majus"},{"thumbnail":"//d2seqvvyy3b8p2.cloudfront.net/4940f6348e9d7df0dce0fe0498a0ae5a.jpg","fullsize":"//d2seqvvyy3b8p2.cloudfront.net/0b3006efbab8c3aeb1b0a74f42a1521e.jpg","caption":"Antirrhinum majus"},{"thumbnail":"//d2seqvvyy3b8p2.cloudfront.net/30e021fb28905a8fd6e4559645a07fa6.jpg","fullsize":"//d2seqvvyy3b8p2.cloudfront.net/cc3ce86ae7f492e37ebe2642998d91e2.jpg","caption":"Antirrhinum majus 'Album'"}]}