{"accepted":true,"author":"L.","kingdom":"Plantae","family":"Ranunculaceae","name":"Aquilegia vulgaris","rank":"Species","snippet":" <b>Common Name</b>: columbine","url":"/taxon/urn:lsid:ipni.org:names:306409-2","fqId":"urn:lsid:ipni.org:names:306409-2","images":[{"thumbnail":"//d2seqvvyy3b8p2.cloudfront.net/261b22d51219baa4899e30dd914a9a5b.jpg","fullsize":"//d2seqvvyy3b8p2.cloudfront.net/559be09fe249574a1520f216d8764e40.jpg","caption":"Aquilegia vulgaris"},{"thumbnail":"//d2seqvvyy3b8p2.cloudfront.net/070a3fad3c3f7fc656df0402d0afa343.jpg","fullsize":"//d2seqvvyy3b8p2.cloudfront.net/6b94dad0833bf111a6fbaf6b39ee4cfe.jpg","caption":"Aquilegia vulgaris"},{"thumbnail":"//d2seqvvyy3b8p2.cloudfront.net/82045fe1e339d3da06bc719a33c16ef5.jpg","fullsize":"//d2seqvvyy3b8p2.cloudfront.net/f76ff7938f18b597bd8cc9eeeaf46e7c.jpg","caption":"Aquilegia vulgaris"}]}