{"accepted":true,"kingdom":"Plantae","family":"Fabaceae","name":"Senna alexandrina var. alexandrina","rank":"Variety","url":"/taxon/urn:lsid:ipni.org:names:77208460-1","fqId":"urn:lsid:ipni.org:names:77208460-1","images":[{"thumbnail":"//d2seqvvyy3b8p2.cloudfront.net/27a48698ca2911600016c28d3eaac0a8.jpg","fullsize":"//d2seqvvyy3b8p2.cloudfront.net/2a7c9b6bc8ab13b73b19d8d041643b62.jpg","caption":"A specimen from Kew's Herbarium"},{"thumbnail":"//d2seqvvyy3b8p2.cloudfront.net/283667035fc4acfe0fee6009730a46a7.jpg","fullsize":"//d2seqvvyy3b8p2.cloudfront.net/19655e699787513904f74027cf8daacc.jpg","caption":"A specimen from Kew's Herbarium"},{"thumbnail":"//d2seqvvyy3b8p2.cloudfront.net/e5ba7f60f8b9158c933e2ce964391fdf.jpg","fullsize":"//d2seqvvyy3b8p2.cloudfront.net/2541cd1a84d9c7cff2d28ca3ecac2591.jpg","caption":"A specimen from Kew's Herbarium"}]}