{"accepted":true,"author":"(Pers.) Greene","kingdom":"Plantae","family":"Fabaceae","name":"Chamaecrista rotundifolia","rank":"Species","url":"/taxon/urn:lsid:ipni.org:names:54723-2","fqId":"urn:lsid:ipni.org:names:54723-2","images":[{"thumbnail":"//d2seqvvyy3b8p2.cloudfront.net/13996396c309f94339e0118add58ed7d.jpg","fullsize":"//d2seqvvyy3b8p2.cloudfront.net/09e55494365b814e27aa9266e2228504.jpg","caption":"Chamaecrista rotundifolia"},{"thumbnail":"//d2seqvvyy3b8p2.cloudfront.net/b990d96bc6f0d51162de9eaf20b7223d.jpg","fullsize":"//d2seqvvyy3b8p2.cloudfront.net/781101d90b519ad07dae2c239727b93b.jpg","caption":"Chamaecrista rotundifolia"},{"thumbnail":"//d2seqvvyy3b8p2.cloudfront.net/15b81a70663efdc3189bde73e731a84d.jpg","fullsize":"//d2seqvvyy3b8p2.cloudfront.net/4118619d222e56c5f33bae046c7d28df.jpg","caption":"A specimen from Kew's Herbarium"}]}