{"accepted":true,"author":"(Christ) G.Kunkel","kingdom":"Plantae","family":"Fabaceae","name":"Chamaecytisus proliferus subsp. palmensis","rank":"Subspecies","url":"/taxon/urn:lsid:ipni.org:names:884965-1","fqId":"urn:lsid:ipni.org:names:884965-1","images":[{"thumbnail":"//d2seqvvyy3b8p2.cloudfront.net/48acff2a5784c5365409b6c1121abe0f.jpg","fullsize":"//d2seqvvyy3b8p2.cloudfront.net/17660d3d6900dbbc1205094a5fe3b1b5.jpg","caption":"Chamaecytisus palmensis"},{"thumbnail":"//d2seqvvyy3b8p2.cloudfront.net/c019ee461aaf1475be52d31947dcb3b4.jpg","fullsize":"//d2seqvvyy3b8p2.cloudfront.net/dafd9745c58fecb8c00900dc22e4f241.jpg","caption":"Chamaecytisus palmensis"},{"thumbnail":"//d2seqvvyy3b8p2.cloudfront.net/623190c1f4dc1c86e1acc30634db2544.jpg","fullsize":"//d2seqvvyy3b8p2.cloudfront.net/0a770f2e8056840f22da1debfbb90573.jpg","caption":"Chamaecytisus palmensis"}]}