{"accepted":true,"kingdom":"Plantae","family":"Rutaceae","name":"Citrus × aurantium f. aurantium","rank":"Form","url":"/taxon/urn:lsid:ipni.org:names:3287406-4","fqId":"urn:lsid:ipni.org:names:3287406-4","images":[{"thumbnail":"//d2seqvvyy3b8p2.cloudfront.net/12c7fcad588c7d1bf348571135eea0bf.jpg","fullsize":"//d2seqvvyy3b8p2.cloudfront.net/b446ede779d8376722160ff720a74371.jpg","caption":"Citrus aurantium var. myrtifolium"},{"thumbnail":"//d2seqvvyy3b8p2.cloudfront.net/e7ecbb726269f8699b162a504751714f.jpg","fullsize":"//d2seqvvyy3b8p2.cloudfront.net/548eca3468e74604d176a7c6ff8e3e98.jpg","caption":"A specimen from Kew's Herbarium"},{"thumbnail":"//d2seqvvyy3b8p2.cloudfront.net/6acf5c544d10037d335447ea5384d849.jpg","fullsize":"//d2seqvvyy3b8p2.cloudfront.net/e5aefbc34f6abf5bd024f80445e07436.jpg","caption":"Citrus × sinensis"}]}