{"accepted":true,"author":"L.","kingdom":"Plantae","family":"Poaceae","name":"Cynosurus cristatus","rank":"Species","snippet":" <b>Common Name</b>: traneen grass","url":"/taxon/urn:lsid:ipni.org:names:397168-1","fqId":"urn:lsid:ipni.org:names:397168-1","images":[{"thumbnail":"//d2seqvvyy3b8p2.cloudfront.net/6642b692f55d6f5ad8560afc36ba3e50.jpg","fullsize":"//d2seqvvyy3b8p2.cloudfront.net/4c5e3ae393ae368e3d05fd109818e8fd.jpg","caption":"Cynosurus cristatus"},{"thumbnail":"//d2seqvvyy3b8p2.cloudfront.net/dbc53f2107974e5aa59b737e6cf92c2c.jpg","fullsize":"//d2seqvvyy3b8p2.cloudfront.net/8de0bb637e9637418600c6f7889c1209.jpg","caption":"Cynosurus cristatus"},{"thumbnail":"//d2seqvvyy3b8p2.cloudfront.net/3f757a480cbd6f41457bbe62b6233978.jpg","fullsize":"//d2seqvvyy3b8p2.cloudfront.net/9acc74aa98a6ab56a2548da768ab57ef.jpg","caption":"Cynosurus cristatus"}]}