{"accepted":true,"author":"(Schult. & Schult.f.) Backer","kingdom":"Plantae","family":"Poaceae","name":"Dendrocalamus asper","rank":"Species","url":"/taxon/urn:lsid:ipni.org:names:397862-1","fqId":"urn:lsid:ipni.org:names:397862-1","images":[{"thumbnail":"//d2seqvvyy3b8p2.cloudfront.net/4bb8285847e320747c126d4e6dea97fc.jpg","fullsize":"//d2seqvvyy3b8p2.cloudfront.net/68c4695a7d9036203997f7208446a42c.jpg","caption":"A specimen from Kew's Herbarium"},{"thumbnail":"//d2seqvvyy3b8p2.cloudfront.net/35034e872709c8ffea800ed0e7f8dd05.jpg","fullsize":"//d2seqvvyy3b8p2.cloudfront.net/71a2d79987e858e6ef1fb7355b61e608.jpg","caption":"A specimen from Kew's Herbarium"}]}