{"accepted":true,"author":"(Desr.) Kostel.","kingdom":"Plantae","family":"Ebenaceae","name":"Diospyros malabarica","rank":"Species","snippet":" <b>Common Name</b>: mai lang dam (Lao)","url":"/taxon/urn:lsid:ipni.org:names:322658-1","fqId":"urn:lsid:ipni.org:names:322658-1","images":[{"thumbnail":"//d2seqvvyy3b8p2.cloudfront.net/a501a15968750b1690ec46e3653d5301.jpg","fullsize":"//d2seqvvyy3b8p2.cloudfront.net/6af5f91b1081aa7ab8e1bb311b1076c7.jpg","caption":"Diospyros malabarica"},{"thumbnail":"//d2seqvvyy3b8p2.cloudfront.net/872b147f261a9319f0e7cbbf43ea9702.jpg","fullsize":"//d2seqvvyy3b8p2.cloudfront.net/1d7fc901bcb8bfb252fd86bb172d1652.jpg","caption":"Diospyros malabarica"},{"thumbnail":"//d2seqvvyy3b8p2.cloudfront.net/e37afd6d00aa13f86f68a9e3a5e864a4.jpg","fullsize":"//d2seqvvyy3b8p2.cloudfront.net/fb503a8f5501288197a29978033b7825.jpg","caption":"Diospyros malabarica"}]}