{"accepted":true,"author":"(L.) Stapf","kingdom":"Plantae","family":"Poaceae","name":"Hyparrhenia hirta","rank":"Species","snippet":" <b>Common Name</b>: panri pullu","url":"/taxon/urn:lsid:ipni.org:names:405537-1","fqId":"urn:lsid:ipni.org:names:405537-1","images":[{"thumbnail":"//d2seqvvyy3b8p2.cloudfront.net/97ec097457a77ebb3d75634db1e8c886.jpg","fullsize":"//d2seqvvyy3b8p2.cloudfront.net/d78cf45ee289aa7ec1e8ed0b00f11312.jpg","caption":"Hyparrhenia hirta"},{"thumbnail":"//d2seqvvyy3b8p2.cloudfront.net/8c07381f252c4834cde4a3115e858a91.jpg","fullsize":"//d2seqvvyy3b8p2.cloudfront.net/f644c8bc7a803171f82e4a364942fb44.jpg","caption":"Hyparrhenia hirta"},{"thumbnail":"//d2seqvvyy3b8p2.cloudfront.net/2820237f8707b179ab6bdec348bc4de6.jpg","fullsize":"//d2seqvvyy3b8p2.cloudfront.net/bcd86a676e075cc3e7b52322643a538c.jpg","caption":"Hyparrhenia hirta"}]}