{"accepted":true,"author":"L.","kingdom":"Plantae","family":"Asteraceae","name":"Lactuca virosa","rank":"Species","snippet":" <b>Common Name</b>: lettuce","url":"/taxon/urn:lsid:ipni.org:names:329493-2","fqId":"urn:lsid:ipni.org:names:329493-2","images":[{"thumbnail":"//d2seqvvyy3b8p2.cloudfront.net/c28839bef9bb6670bc298193ed493aae.jpg","fullsize":"//d2seqvvyy3b8p2.cloudfront.net/d90d9d810e196ed824906221c37fd9e4.jpg","caption":"Lactuca virosa"},{"thumbnail":"//d2seqvvyy3b8p2.cloudfront.net/b140b95ad75d023077bc8df29d3060e4.jpg","fullsize":"//d2seqvvyy3b8p2.cloudfront.net/2e155923af33933a372b230ce7cb5489.jpg","caption":"Lactuca virosa"},{"thumbnail":"//d2seqvvyy3b8p2.cloudfront.net/76743175c0c9560445d19e38ae110965.jpg","fullsize":"//d2seqvvyy3b8p2.cloudfront.net/db91bd978f97ee3753706cd45a7a0514.jpg","caption":"Lactuca virosa"}]}