{"accepted":true,"author":"L.","kingdom":"Plantae","family":"Moraceae","name":"Morus nigra","rank":"Species","snippet":" <b>Common Name</b>: common mulberry","url":"/taxon/urn:lsid:ipni.org:names:854688-1","fqId":"urn:lsid:ipni.org:names:854688-1","images":[{"thumbnail":"//d2seqvvyy3b8p2.cloudfront.net/9211eaf42fa2f4738cd5e885d8bc8f0d.jpg","fullsize":"//d2seqvvyy3b8p2.cloudfront.net/ff9ba53e4793eca78c4836604de75ca6.jpg","caption":"Germany, Sturms Flora von Deutschland (1900-1906)"},{"thumbnail":"//d2seqvvyy3b8p2.cloudfront.net/b295c2346d837f7574087abddb67a59a.jpg","fullsize":"//d2seqvvyy3b8p2.cloudfront.net/f7cb258d2c92a30e97687664a775d385.jpg","caption":"A specimen from Kew's Herbarium"},{"thumbnail":"//d2seqvvyy3b8p2.cloudfront.net/1af4ffebfc676e686568545b6034ba38.jpg","fullsize":"//d2seqvvyy3b8p2.cloudfront.net/d1b1609a5e7737c389b1d56fd9027527.jpg","caption":"Morus nigra"}]}