{"accepted":true,"author":"Wurmb","kingdom":"Plantae","family":"Arecaceae","name":"Nypa fruticans","rank":"Species","snippet":" <b>Common Name</b>: mangrove palm","url":"/taxon/urn:lsid:ipni.org:names:668507-1","fqId":"urn:lsid:ipni.org:names:668507-1","images":[{"thumbnail":"//d2seqvvyy3b8p2.cloudfront.net/2e37adec11efdf1a2f284ff4e1f6728b.jpg","fullsize":"//d2seqvvyy3b8p2.cloudfront.net/4a49b2af0bcccf56d6e97101f73eaf8f.jpg","caption":"Nypa fruticans, Tanjung Warari, Biak, Indonesia (William J. Baker)"},{"thumbnail":"//d2seqvvyy3b8p2.cloudfront.net/91fb365a6894566d41ee522853c66588.jpg","fullsize":"//d2seqvvyy3b8p2.cloudfront.net/529e3c60f6baf5b6718023d964d15311.jpg","caption":"Nypa fruticans, Montgomery Botanical Centre, USA (William J. Baker)"},{"thumbnail":"//d2seqvvyy3b8p2.cloudfront.net/fbab4db17c48280fbcc54a5f01054305.jpg","fullsize":"//d2seqvvyy3b8p2.cloudfront.net/6f5ebedef3d6c78a4806c82248b47671.jpg","caption":"Nypa fruticans, Berbak, Indonesia (John Dransfield)"}]}