{"accepted":true,"author":"Poir.","kingdom":"Plantae","family":"Poaceae","name":"Paspalum dilatatum","rank":"Species","url":"/taxon/urn:lsid:ipni.org:names:414070-1","fqId":"urn:lsid:ipni.org:names:414070-1","images":[{"thumbnail":"//d2seqvvyy3b8p2.cloudfront.net/4ce396a6d4a884580a3a688f8a0c4bdb.jpg","fullsize":"//d2seqvvyy3b8p2.cloudfront.net/a55df2b7ac4cdb28bfb3261b205d0f2d.jpg","caption":"Paspalum dilatatum"},{"thumbnail":"//d2seqvvyy3b8p2.cloudfront.net/72810235f137945a656c67b4c5601f4e.jpg","fullsize":"//d2seqvvyy3b8p2.cloudfront.net/62242ccef540e94a07466558423cb12a.jpg","caption":"Paspalum dilatatum"},{"thumbnail":"//d2seqvvyy3b8p2.cloudfront.net/90575ffe62c823813ff1f42db0e6d555.jpg","fullsize":"//d2seqvvyy3b8p2.cloudfront.net/51d7301fcf32d39209eb89886c0285fd.jpg","caption":"Paspalum dilatatum"}]}