{"accepted":true,"author":"L.","kingdom":"Plantae","family":"Anacardiaceae","name":"Pistacia lentiscus","rank":"Species","snippet":" <b>Common Name</b>: shinia","url":"/taxon/urn:lsid:ipni.org:names:70253-1","fqId":"urn:lsid:ipni.org:names:70253-1","images":[{"thumbnail":"//d2seqvvyy3b8p2.cloudfront.net/ffed5469228a1bdcb9216097314ec859.jpg","fullsize":"//d2seqvvyy3b8p2.cloudfront.net/960e1a03d1054a095892f46af29f109a.jpg","caption":"Pistachia lentiscus"},{"thumbnail":"//d2seqvvyy3b8p2.cloudfront.net/36908dea87bbfa1842b1d95d8d7600a5.jpg","fullsize":"//d2seqvvyy3b8p2.cloudfront.net/f175113970eb049ff38987e9d1a0ff33.jpg","caption":"Pistachia lentiscus"},{"thumbnail":"//d2seqvvyy3b8p2.cloudfront.net/609e94258aa026d8ed765ff9f9a116f8.jpg","fullsize":"//d2seqvvyy3b8p2.cloudfront.net/bd31b5e6137aab4d0c7401bc4aee666e.jpg","caption":"Pistachia lentiscus"}]}