{"accepted":true,"author":"(Jaub. & Spach) Nevski","kingdom":"Plantae","family":"Plumbaginaceae","name":"Psylliostachys","rank":"Genus","snippet":" <b>General</b>:  to the inflorescence of <em>Plantago</em> <em>psyllium</em>).","url":"/taxon/urn:lsid:ipni.org:names:32165-1","fqId":"urn:lsid:ipni.org:names:32165-1","images":[{"thumbnail":"//d2seqvvyy3b8p2.cloudfront.net/c0643d1b99f4e9c8ff8354ccc83a2388.jpg","fullsize":"//d2seqvvyy3b8p2.cloudfront.net/b42621dbe91f01510fdfacfe11a08ceb.jpg","caption":"Psylliostachys suworowii"},{"thumbnail":"//d2seqvvyy3b8p2.cloudfront.net/68fb0b62440be5f5e32006903b2f2e53.jpg","fullsize":"//d2seqvvyy3b8p2.cloudfront.net/d254460a93b1b6bb723667e881f589f6.jpg","caption":"Psylliostachys suworowii"},{"thumbnail":"//d2seqvvyy3b8p2.cloudfront.net/b461f1b360e16e4a6f602138f2ef519b.jpg","fullsize":"//d2seqvvyy3b8p2.cloudfront.net/9ca547f2b4ddee74b19745474d8c5fa0.jpg","caption":"Psylliostachys suworowii"}]}