{"accepted":true,"author":"(L.) Merr.","kingdom":"Plantae","family":"Fabaceae","name":"Sesbania sesban","rank":"Species","url":"/taxon/urn:lsid:ipni.org:names:518533-1","fqId":"urn:lsid:ipni.org:names:518533-1","images":[{"thumbnail":"//d2seqvvyy3b8p2.cloudfront.net/fd27ef587b06d52682e1fb2db5a4f4b5.jpg","fullsize":"//d2seqvvyy3b8p2.cloudfront.net/8df9179d23a47db82b89be352353143b.jpg","caption":"Sesbania sesban"},{"thumbnail":"//d2seqvvyy3b8p2.cloudfront.net/d0b80e89419d943e34deaaf0050064db.jpg","fullsize":"//d2seqvvyy3b8p2.cloudfront.net/b386e224a31f7fcb598f309db82b7aac.jpg","caption":"Sesbania sesban"},{"thumbnail":"//d2seqvvyy3b8p2.cloudfront.net/4f9fc071c83d3a3291b2f10b7cb77f87.jpg","fullsize":"//d2seqvvyy3b8p2.cloudfront.net/b1fb21abb7c5ded160af739b5497cd7f.jpg","caption":"Sesbania sesban"}]}