{"accepted":true,"author":"(L.) Scop.","kingdom":"Plantae","family":"Brassicaceae","name":"Sisymbrium officinale","rank":"Species","url":"/taxon/urn:lsid:ipni.org:names:289589-1","fqId":"urn:lsid:ipni.org:names:289589-1","images":[{"thumbnail":"//d2seqvvyy3b8p2.cloudfront.net/5968b6518faebeda63b88fc4cc76b992.jpg","fullsize":"//d2seqvvyy3b8p2.cloudfront.net/628a89b080e6398b8e2ab21a9ea61ae7.jpg","caption":"Sisymbrium officinale"},{"thumbnail":"//d2seqvvyy3b8p2.cloudfront.net/7a166e60ff4c2456e320ac485ad19329.jpg","fullsize":"//d2seqvvyy3b8p2.cloudfront.net/847a55c11318a30cbcbe2ee8489f0989.jpg","caption":"Sisymbrium officinale"},{"thumbnail":"//d2seqvvyy3b8p2.cloudfront.net/7714f7d62ef81c3badaa596dfba9ace0.jpg","fullsize":"//d2seqvvyy3b8p2.cloudfront.net/618397527ad7df6331ba4050fbe915e6.jpg","caption":"Sisymbrium officinale"}]}