{"accepted":true,"author":"(L.) Kunth","kingdom":"Plantae","family":"Poaceae","name":"Macrochloa tenacissima","rank":"Species","url":"/taxon/urn:lsid:ipni.org:names:407732-1","fqId":"urn:lsid:ipni.org:names:407732-1","images":[{"thumbnail":"//d2seqvvyy3b8p2.cloudfront.net/34901ccc840c285b7995db9eb21e5ed1.jpg","fullsize":"//d2seqvvyy3b8p2.cloudfront.net/e4ee48048d92c40477e0587c03c84bf6.jpg","caption":"Macrochloa tenacissima"},{"thumbnail":"//d2seqvvyy3b8p2.cloudfront.net/60b75162d24dd80fcb13e3d628f671b4.jpg","fullsize":"//d2seqvvyy3b8p2.cloudfront.net/780708dce9c2cf4ae81043b75f383635.jpg","caption":"A specimen from Kew's Herbarium"}]}