{"accepted":true,"author":"L.","kingdom":"Plantae","family":"Lamiaceae","name":"Thymus serpyllum","rank":"Species","snippet":" <b>Common Name</b>: wild thyme","url":"/taxon/urn:lsid:ipni.org:names:30066276-2","fqId":"urn:lsid:ipni.org:names:30066276-2","images":[{"thumbnail":"//d2seqvvyy3b8p2.cloudfront.net/fb4899bf84e880c2be2940cbc36db3b2.jpg","fullsize":"//d2seqvvyy3b8p2.cloudfront.net/20d221913e922b0a9f2e981fb389c63e.jpg","caption":"Thymus serpyllum"},{"thumbnail":"//d2seqvvyy3b8p2.cloudfront.net/50dcc60c7a980de98681a0fb2cf4294b.jpg","fullsize":"//d2seqvvyy3b8p2.cloudfront.net/1b8b3ab120a02d1dcae258e452f7c9d9.jpg","caption":"Thymus serpyllum"},{"thumbnail":"//d2seqvvyy3b8p2.cloudfront.net/6969f1b8680e51d7dcacc5922872fa8e.jpg","fullsize":"//d2seqvvyy3b8p2.cloudfront.net/f77bcebaae22e9dead67eefa595615a4.jpg","caption":"Thymus serpyllum"}]}