{"accepted":true,"author":"L.","kingdom":"Plantae","family":"Asteraceae","name":"Tussilago farfara","rank":"Species","snippet":" <b>Common Name</b>: k'uan tung hua","url":"/taxon/urn:lsid:ipni.org:names:256904-1","fqId":"urn:lsid:ipni.org:names:256904-1","images":[{"thumbnail":"//d2seqvvyy3b8p2.cloudfront.net/23b3a31b6c1836ec94e36c5e41c7aacc.jpg","fullsize":"//d2seqvvyy3b8p2.cloudfront.net/15103b5f993e7cb5b984100e358a85cf.jpg","caption":"Tussilago farfara"},{"thumbnail":"//d2seqvvyy3b8p2.cloudfront.net/83256f5f6faf4e63ade9a65ede654b6c.jpg","fullsize":"//d2seqvvyy3b8p2.cloudfront.net/c8097f0231d5021261c0c476dc895077.jpg","caption":"Tussilago farfara"},{"thumbnail":"//d2seqvvyy3b8p2.cloudfront.net/75f3e8fe347778aafaeed99010ee9b3b.jpg","fullsize":"//d2seqvvyy3b8p2.cloudfront.net/dfe5d25a3a84f9f38db8cadea2d38980.jpg","caption":"Tussilago farfara"}]}