{"accepted":true,"author":"(Burch.) A.Schreib.","kingdom":"Plantae","family":"Fabaceae","name":"Tylosema esculentum","rank":"Species","snippet":" <b>Common Name</b>: gemsbok beans","url":"/taxon/urn:lsid:ipni.org:names:524263-1","fqId":"urn:lsid:ipni.org:names:524263-1","images":[{"thumbnail":"//storage.googleapis.com/powop-assets/lowo/Tylosema%20esculentum_thumbnail.jpg","fullsize":"//storage.googleapis.com/powop-assets/lowo/Tylosema%20esculentum_fullsize.jpg","caption":"Tylosema esculentum (Burch.) A. Schreib."},{"thumbnail":"//storage.googleapis.com/powop-assets/lowo/Tylosema%20esculenta-Botswana-Helen%20Moss-3200_thumbnail.jpg","fullsize":"//storage.googleapis.com/powop-assets/lowo/Tylosema%20esculenta-Botswana-Helen%20Moss-3200_fullsize.jpg","caption":"Tylosema esculentum (Burch.) A. Schreib."},{"thumbnail":"//storage.googleapis.com/powop-assets/lowo/Tylosema%20esculenta-Botswana-Helen%20Moss-3201_thumbnail.jpg","fullsize":"//storage.googleapis.com/powop-assets/lowo/Tylosema%20esculenta-Botswana-Helen%20Moss-3201_fullsize.jpg","caption":"Tylosema esculentum (Burch.) A. Schreib."}]}