{"fullsize":"Baccaurea ramiflora fullsize.jpg","thumbnail":"Baccaurea ramiflora thumbnail.jpg","family":"Phyllanthaceae","ph":null,"temp":null,"genus":"Baccaurea","kingdom":"Plantae","taxon":"https://powo.science.kew.org//taxon/urn:lsid:ipni.org:names:339677-1","kategori":null,"difficulty":"MEDIUM","description":"Baccaurea ramiflora adalah pohon buah tropis yang menghasilkan buah berwarna kuning kemerahan dengan rasa manis asam. Tumbuh baik di iklim lembap tropis dengan ketinggian hingga 10 meter.","nama_ilmiah":"Baccaurea ramiflora","common_names":null,"min_panen":0,"max_panen":0,"plant_care":{"watering":"Menjaga kelembaban tanah dengan penyiraman 2-3 kali seminggu, hindari genangan air","pruning":"Pangkas cabang mati dan menipiskan tajuk setelah panen untuk merangsang pertumbuhan buah","fertilization":"Berikan pupuk kandang saat penanaman, lalu pupuk NPK seimbang setiap 3 bulan sekali","sunlight":"Menyukai sinar matahari penuh hingga teduhan ringan (4-6 jam sehari)","pest_disease_management":"Cegah hama seperti kutu daun dan ulat dengan semprotan insektisida nabati, serta fungisida untuk jamur"},"product_system":{"rumah_tangga":"Konsumsi buah segar untuk keluarga","komersial":"Budidaya skala kebun untuk penjualan buah segar dan olahan seperti selai","industri":"Ekstraksi nutrisi untuk minuman kesehatan dan kosmetik"},"common_name":"Anggur Burma","prune_guide":"https://www.blogpertanian.com/panduan-pemangkasan-baccaurea-ramiflora"}