{"fullsize":"Chlorophora excelsa fullsize.jpg","thumbnail":"Chlorophora excelsa thumbnail.jpg","family":"Moraceae","ph":null,"temp":null,"genus":"Chlorophora","kingdom":"Plantae","taxon":"https://powo.science.kew.org//taxon/urn:lsid:ipni.org:names:910901-1","kategori":null,"difficulty":"HARD","description":"Chlorophora excelsa atau Iroko adalah pohon keras tropis asal Afrika Barat, terkenal dengan kayunya yang tahan lama dan tahan air. Tinggi dapat mencapai 40 m dengan kulit tebal dan retak-retak. Kayunya sering digunakan untuk konstruksi dan pembuatan perabot.","nama_ilmiah":"Chlorophora excelsa","common_names":null,"min_panen":0,"max_panen":0,"plant_care":{"watering":"Penyiraman sedang, cukup lembab namun hindari genangan air, frekuensi 1–2 kali seminggu tergantung kondisi tanah","pruning":"Pemangkasan minimal, hanya untuk membuang cabang mati atau rusak setelah musim hujan","fertilization":"Pemberian pupuk NPK seimbang setiap 3 bulan sekali, ditambah kompos organik di musim hujan","sunlight":"Sinar matahari penuh hingga teduh parsial","pest_disease_management":"Pemantauan rutin terhadap serangan kumbang kayu, rayap, dan jamur akar; gunakan insektisida dan fungisida sesuai kebutuhan"},"product_system":{"rumah_tangga":"Jarang digunakan sebagai tanaman hias; lebih sering ditanam di halaman luas sebagai pohon peneduh","komersial":"Dikultur secara komersial untuk produksi kayu mewah dan bahan bangunan","industri":"Bahan baku utama untuk konstruksi, pembuatan kapal, dan perabot kelas atas"},"common_name":"Iroko","prune_guide":"Tanaman ini tidak dapat dipangkas"}