{"fullsize":null,"thumbnail":null,"family":null,"ph":null,"temp":null,"genus":"Crotalaria","kingdom":null,"taxon":null,"kategori":null,"difficulty":"MEDIUM","description":"Crotalaria brevides var. brevides adalah tanaman leguminosa yang tumbuh tegak hingga setinggi 30–60 cm. Sering digunakan sebagai tanaman penutup tanah dan pupuk hijau karena kemampuannya memfiksasi nitrogen, meningkatkan kesuburan tanah, dan menekan gulma.","nama_ilmiah":"Crotalaria brevides var. brevides","common_names":null,"min_panen":0,"max_panen":0,"plant_care":{"watering":"Sirami secara sedang, biarkan media agak mengering di antara penyiraman untuk menghindari pembusukan akar.","pruning":"Pemangkasan tidak diperlukan; cukup buang daun atau batang yang mati untuk menjaga kesehatan tanaman.","fertilization":"Berikan pupuk NPK seimbang (contoh 10-10-10) setiap 4–6 minggu sekali selama masa pertumbuhan.","sunlight":"Butuh sinar matahari penuh minimal 6–8 jam per hari, tetapi toleran terhadap cahaya sedang.","pest_disease_management":"Waspadai kutu daun dan ulat; gunakan insektisida organik seperti minyak nimba dan fungisida bila muncul gejala jamur."},"product_system":{"rumah_tangga":"Dapat ditanam di pekarangan sebagai penutup tanah dan pupuk hijau pada kebun sayur rumah.","komersial":"Dibudidayakan secara besar untuk produksi pupuk hijau komersial dan pakan ternak.","industri":"Potensial untuk fitoremediasi tanah tercemar serta ekstraksi senyawa bioaktif, namun penggunaan industri masih terbatas."},"common_name":"Crotalaria brevides","prune_guide":"Tanaman ini tidak dapat dipangkas"}