{"fullsize":"Guaiacum sanctum fullsize.jpg","thumbnail":"Guaiacum sanctum thumbnail.jpg","family":"Zygophyllaceae","ph":null,"temp":null,"genus":"Guaiacum","kingdom":"Plantae","taxon":"https://powo.science.kew.org//taxon/urn:lsid:ipni.org:names:873256-1","kategori":null,"difficulty":"MEDIUM","description":"Guaiacum sanctum adalah pohon tropis lambat tumbuh yang menghasilkan kayu sangat keras dan resin bernilai tinggi, sering digunakan untuk kayu mebel dan bahan obat tradisional.","nama_ilmiah":"Guaiacum sanctum","common_names":null,"min_panen":0,"max_panen":0,"plant_care":{"watering":"Penyiraman sedang; siram 1–2 kali seminggu, biarkan lapisan atas tanah sedikit kering sebelum disiram kembali.","pruning":"Pangkas ringan untuk membuang cabang mati atau rusak pada awal musim semi dengan alat steril.","fertilization":"Berikan pupuk NPK seimbang setiap 3 bulan sekali dan tambahkan kompos matang setahun sekali.","sunlight":"Memerlukan sinar matahari penuh hingga teduh parsial (4–6 jam cahaya matahari langsung sehari).","pest_disease_management":"Waspadai serangan kutu daun dan kumbang kayu; atasi dengan semprotan insektisida nabati atau lapisan insektisida sesuai kebutuhan."},"product_system":{"rumah_tangga":"Ditanam sebagai tanaman hias di pekarangan atau bonsai.","komersial":"Sumber kayu keras untuk pembuatan mebel, suvenir, dan kerajinan.","industri":"Ekstraksi resin untuk obat-obatan tradisional dan bahan industri."},"common_name":"Pohon suci","prune_guide":"https://www.tanamaninspirasi.com/memangkas-pohon-lignum-vitae"}