{"fullsize":"Hevea brasiliensis fullsize.jpg","thumbnail":"Hevea brasiliensis thumbnail.jpg","family":"Euphorbiaceae","ph":null,"temp":null,"genus":"Hevea","kingdom":"Plantae","taxon":"https://powo.science.kew.org//taxon/urn:lsid:ipni.org:names:349913-1","kategori":null,"difficulty":"MEDIUM","description":"Hevea brasiliensis adalah pohon tropis penghasil lateks yang menjadi bahan baku utama karet alam. Memiliki daun majemuk, tumbuh subur di dataran rendah dan lembap.","nama_ilmiah":"Hevea brasiliensis","common_names":null,"min_panen":0,"max_panen":0,"plant_care":{"watering":"Tanah selalu lembab, siram 2–3 kali seminggu untuk menjaga kelembaban, hindari genangan air","pruning":"Pangkas cabang mati dan tunas kompetitor, bentuk tajuk saat muda, lakukan setelah musim panen getah","fertilization":"Pemberian pupuk kandang saat tanam, aplikasikan pupuk NPK (15:15:15) setiap 3–4 bulan sekali","sunlight":"Memerlukan sinar matahari penuh minimal 6–8 jam per hari","pest_disease_management":"Cegah blas daun dan busuk pangkal batang dengan sanitasi kebun, semprot fungisida/insektisida sesuai anjuran, padatkan rotasi tanaman"},"product_system":{"rumah_tangga":"Dapat ditanam sebagai tanaman hias besar atau pot, getah sedikit cocok untuk kerajinan","komersial":"Ditanam di perkebunan skala menengah hingga besar untuk produksi lateks","industri":"Bahan baku utama karet alam untuk ban, sarung tangan, dan berbagai produk karet lainnya"},"common_name":"Pohon Karet","prune_guide":"https://www.bibit.id/artikel/cara-pemangkasan-pohon-karet"}