{"fullsize":"Khaya senegalensis fullsize.jpg","thumbnail":"Khaya senegalensis thumbnail.jpg","family":"Meliaceae","ph":null,"temp":null,"genus":"Khaya","kingdom":"Plantae","taxon":"https://powo.science.kew.org//taxon/urn:lsid:ipni.org:names:578867-1","kategori":null,"difficulty":"MEDIUM","description":"Khaya senegalensis atau Mahoni Senegal adalah pohon tropis besar asli Afrika Barat. Kayunya berkualitas tinggi, tahan lama, dan banyak digunakan untuk industri mebel dan konstruksi. Tumbuh baik pada iklim tropis dengan curah hujan sedang hingga tinggi dan tanah yang gembur serta drainase baik.","nama_ilmiah":"Khaya senegalensis","common_names":null,"min_panen":0,"max_panen":0,"plant_care":{"watering":"Penyiraman sedang; jaga kelembaban tanah tetapi hindari genangan air. Siram 2-3 kali seminggu pada musim kemarau.","pruning":"Lakukan pemangkasan minimal untuk membuang ranting mati atau rusak, waktu terbaik setelah musim hujan.","fertilization":"Pemberian pupuk NPK seimbang (10-10-10) setiap 3 bulan sekali; tambahkan kompos atau pupuk kandang di pangkal.","sunlight":"Tumbuhan ini membutuhkan sinar matahari penuh hingga teduh ringan; ideal ditanam di lokasi terbuka.","pest_disease_management":"Waspadai serangan rayap, ulat daun, dan penyakit jamur akar; gunakan insektisida alami dan fungisida sesuai dosis."},"product_system":{"rumah_tangga":"Sebagai pohon peneduh dan estetika di halaman besar; udara lebih sejuk","komersial":"Budidaya untuk penjualan bibit dan kayu olahan pada skala menengah","industri":"Sumber kayu keras berkualitas untuk mebel, lantai, veneer, dan konstruksi berat"},"common_name":"Mahoni Senegal","prune_guide":"https://www.youtube.com/watch?v=Hu7Y_YRGXBM"}