{"fullsize":"Paspalum notatum fullsize.jpg","thumbnail":"Paspalum notatum thumbnail.jpg","family":"Poaceae","ph":null,"temp":null,"genus":"Paspalum","kingdom":"Plantae","taxon":"https://powo.science.kew.org//taxon/urn:lsid:ipni.org:names:414477-1","kategori":null,"difficulty":"EASY","description":"Rumput hijau tahunan atau abadi yang tahan kekeringan, ideal untuk halaman, padang golf, dan pakan ternak.","nama_ilmiah":"Paspalum notatum","common_names":null,"min_panen":0,"max_panen":0,"plant_care":{"watering":"Penyiraman sedang, 2-3 kali seminggu di musim kering untuk menjaga kelembapan tanah; toleran kekeringan setelah mapan.","pruning":"Pemotongan rutin hingga ketinggian 5-7 cm setiap 3-4 minggu untuk merangsang pertumbuhan yang rapi.","fertilization":"Pemupukan NPK seimbang (misal 10-10-10) 2-3 kg per 100 m² setiap 6-8 minggu; tingkatkan nitrogen untuk pertumbuhan hijau.","sunlight":"Membutuhkan sinar matahari penuh minimal 6-8 jam per hari.","pest_disease_management":"Pantau hama seperti ulat dan kutu; cegah penyakit jamur dengan drainase baik dan aplikasikan fungisida jika diperlukan."},"product_system":{"rumah_tangga":"Sebagai rumput halaman rumah, perawatan rendah dan tahan pijakan ringan.","komersial":"Cocok untuk lapangan golf, stadion, dan taman kota dengan perawatan intensif.","industri":"Digunakan sebagai pakan ternak hijauan; dapat diolah menjadi silase."},"common_name":"Rumput Bahia","prune_guide":"https://www.youtube.com/watch?v=Hx8KLnguYIM"}