{"fullsize":"Stylosanthes seabrana fullsize.jpg","thumbnail":"Stylosanthes seabrana thumbnail.jpg","family":"Fabaceae","ph":null,"temp":null,"genus":"Stylosanthes","kingdom":"Plantae","taxon":"https://powo.science.kew.org//taxon/urn:lsid:ipni.org:names:325593-2","kategori":null,"difficulty":"EASY","description":"Stylosanthes seabrana adalah tanaman leguminosa yang sering digunakan sebagai pakan ternak dan penutup tanah. Memiliki kemampuan fiksasi nitrogen di akar sehingga baik untuk perbaikan kesuburan tanah. Tumbuh cepat dan toleran terhadap kondisi tanah marginal.","nama_ilmiah":"Stylosanthes seabrana","common_names":null,"min_panen":0,"max_panen":0,"plant_care":{"watering":"Menyiram secara teratur, cukup lembab namun tidak tergenang","pruning":"Pangkas setiap 4-6 minggu untuk merangsang pertumbuhan dan mencegah penumpukan massa tua","fertilization":"Biasanya tidak memerlukan pupuk nitrogen karena kemampuan fiksasi, tambah pupuk fosfor ketika tanah miskin","sunlight":"Tumbuh optimal di bawah sinar matahari penuh minimal 6-8 jam per hari","pest_disease_management":"Cermati gejala penyakit seperti layu akar atau jamur, kontrol hama kutu daun dan ulat dengan insektisida nabati atau mekanis"},"product_system":{"rumah_tangga":"Dapat digunakan sebagai penutup tanah atau tanaman pakan untuk hewan peliharaan di pekarangan rumah","komersial":"Budidaya skala komersial untuk pakan ternak hijauan","industri":"Digunakan dalam industri pakan ternak serta rehabilitasi lahan kritis dan konservasi tanah"},"common_name":"Stylo Seabra","prune_guide":"https://www.youtube.com/watch?v=example"}